rstfmt/__init__.py
rstfmt/__main__.py
rstfmt/_version.py
rstfmt/debug.py
rstfmt/rst_extras.py
rstfmt/rstfmt.py
rstfmt/server.py
rstfmt-0.0.14.dist-info/LICENSE
rstfmt-0.0.14.dist-info/METADATA
rstfmt-0.0.14.dist-info/WHEEL
rstfmt-0.0.14.dist-info/entry_points.txt
rstfmt-0.0.14.dist-info/top_level.txt
rstfmt-0.0.14.dist-info/RECORD
