Metadata-Version: 2.1
Name: rstfmt
Version: 0.0.14
Summary: A formatter for reStructuredText
Home-page: https://github.com/dzhu/rstfmt
Author: Danny Zhu
Author-email: dzhu@dzhu.us
License: MIT
Classifier: Development Status :: 4 - Beta
Classifier: Environment :: Console
Classifier: Intended Audience :: Developers
Classifier: License :: OSI Approved :: MIT License
Classifier: Topic :: Documentation
Classifier: Topic :: Documentation :: Sphinx
Classifier: Topic :: Software Development :: Documentation
Requires-Python: >=3.7
License-File: LICENSE
Requires-Dist: black >=22.1.0
Requires-Dist: docutils >=0.12
Requires-Dist: sphinx >=2.4.0
Provides-Extra: d
Requires-Dist: aiohttp >=3.3.2 ; extra == 'd'
